lucidmq-0.1.1.dist-info/METADATA
lucidmq-0.1.1.dist-info/WHEEL
pylucidmq/__init__.py
pylucidmq/pylucidmq.cpython-312-darwin.so
lucidmq-0.1.1.dist-info/RECORD
