Metadata-Version: 2.3
Name: lucidmq
Version: 0.1.1
Classifier: Programming Language :: Rust
Classifier: Programming Language :: Python :: Implementation :: CPython
Classifier: Programming Language :: Python :: Implementation :: PyPy
License: Apache-2.0
Requires-Python: >=3.7
